CONTRIBUTORS.txt
LICENSE.txt
MANIFEST.in
README.rst
distribute_setup.py
requirements.txt
setup.cfg
setup.py
docs/api.rst
docs/conf.py
docs/index.rst
docs/make.bat
docs/run.py
docs/__pycache__/conf.cpython-33.pyc
docs/__pycache__/run.cpython-33.pyc
docs/_templates/module.rst
docs/_themes/bootstrap/globaltoc.html
docs/_themes/bootstrap/layout.html
docs/_themes/bootstrap/localtoc.html
docs/_themes/bootstrap/relations.html
docs/_themes/bootstrap/searchbox.html
docs/_themes/bootstrap/sourcelink.html
docs/_themes/bootstrap/theme.conf
docs/_themes/bootstrap/static/bootstrap-responsive.css
docs/_themes/bootstrap/static/bootstrap-sphinx.css_t
docs/_themes/bootstrap/static/bootstrap.css
docs/_themes/bootstrap/static/bootstrap.js
docs/_themes/bootstrap/static/jquery.js
docs/_themes/bootstrap/static/img/glyphicons-halflings-white.png
docs/_themes/bootstrap/static/img/glyphicons-halflings.png
docs/api/everest.batch.rst
docs/api/everest.configuration.rst
docs/api/everest.directives.rst
docs/api/everest.entities.aggregates.rst
docs/api/everest.entities.attributes.rst
docs/api/everest.entities.base.rst
docs/api/everest.entities.interfaces.rst
docs/api/everest.entities.repository.rst
docs/api/everest.entities.system.rst
docs/api/everest.entities.utils.rst
docs/api/everest.exceptions.rst
docs/api/everest.ini.rst
docs/api/everest.interfaces.rst
docs/api/everest.messaging.rst
docs/api/everest.mime.rst
docs/api/everest.orm.rst
docs/api/everest.querying.base.rst
docs/api/everest.querying.filtering.rst
docs/api/everest.querying.filterparser.rst
docs/api/everest.querying.interfaces.rst
docs/api/everest.querying.operators.rst
docs/api/everest.querying.orderparser.rst
docs/api/everest.querying.specifications.rst
docs/api/everest.querying.utils.rst
docs/api/everest.relationship.rst
docs/api/everest.renderers.rst
docs/api/everest.repository.rst
docs/api/everest.representers.atom.rst
docs/api/everest.representers.attributes.rst
docs/api/everest.representers.base.rst
everest.egg-info/PKG-INFO
everest.egg-info/SOURCES.txt
everest.egg-info/dependency_links.txt
everest.egg-info/entry_points.txt
everest.egg-info/not-zip-safe
everest.egg-info/requires.txt
everest.egg-info/top_level.txt
