Metadata-Version: 1.1
Name: everest
Version: 1.0
Summary: everest
Home-page: https://github.com/cenix/everest
Author: F. Oliver Gathmann
Author-email: fogathmann at gmail.com
License: MIT
Keywords: REST web wsgi pyramid
Platform: UNKNOWN
Classifier: Development Status :: 5 - Production/Stable
Classifier: Environment :: Web Environment
Classifier: Framework :: Pyramid
Classifier: Intended Audience :: Developers
Classifier: Intended Audience :: Information Technology
Classifier: License :: OSI Approved :: MIT License
Classifier: Programming Language :: Python
Classifier: Topic :: Internet :: WWW/HTTP :: WSGI
